brainglobe_stitch/__init__.py
brainglobe_stitch/big_stitcher_bridge.py
brainglobe_stitch/bigstitcher_macro.ijm
brainglobe_stitch/file_utils.py
brainglobe_stitch/image_mosaic.py
brainglobe_stitch/napari.yaml
brainglobe_stitch/stitching_widget.py
brainglobe_stitch/tile.py
brainglobe_stitch-0.0.1.dist-info/LICENSE
brainglobe_stitch-0.0.1.dist-info/METADATA
brainglobe_stitch-0.0.1.dist-info/WHEEL
brainglobe_stitch-0.0.1.dist-info/entry_points.txt
brainglobe_stitch-0.0.1.dist-info/top_level.txt
brainglobe_stitch-0.0.1.dist-info/RECORD
