Metadata-Version: 2.1
Name: brainglobe-stitch
Version: 0.0.1
Summary: A tool to stich large tiled datasets generated by the mesoSPIM.
Author-email: Brainglobe Developers <hello@brainglobe.info>
License: BSD-3-Clause
Project-URL: Homepage, https://brainglobe.info
Project-URL: Bug Tracker, https://github.com/brainglobe/brainglobe-stitch/issues
Project-URL: Documentation, https://github.com/brainglobe/brainglobe-stitch#README.md
Project-URL: Source Code, https://github.com/brainglobe/brainglobe-stitch
Project-URL: User Support, https://forum.image.sc/tag/brainglobe
Classifier: Development Status :: 2 - Pre-Alpha
Classifier: Framework :: napari
Classifier: Programming Language :: Python
Classifier: Programming Language :: Python :: 3
Classifier: Programming Language :: Python :: 3.10
Classifier: Programming Language :: Python :: 3.11
Classifier: Programming Language :: Python :: 3.12
Classifier: Operating System :: OS Independent
Classifier: License :: OSI Approved :: BSD License
Classifier: Topic :: Scientific/Engineering :: Image Processing
Requires-Python: >=3.10
License-File: LICENSE
Requires-Dist: napari>=0.4.18
Requires-Dist: brainglobe-utils>=0.3.4
Requires-Dist: h5py
Requires-Dist: napari-ome-zarr
Requires-Dist: ome-zarr
Requires-Dist: zarr
Requires-Dist: numpy
Requires-Dist: qtpy
Requires-Dist: tifffile
Provides-Extra: dev
Requires-Dist: pytest; extra == "dev"
Requires-Dist: pytest-cov; extra == "dev"
Requires-Dist: pytest-mock; extra == "dev"
Requires-Dist: pytest-qt; extra == "dev"
Requires-Dist: pyqt5; extra == "dev"
Requires-Dist: coverage; extra == "dev"
Requires-Dist: tox; extra == "dev"
Requires-Dist: pooch; extra == "dev"
Requires-Dist: black; extra == "dev"
Requires-Dist: mypy; extra == "dev"
Requires-Dist: pre-commit; extra == "dev"
Requires-Dist: ruff; extra == "dev"
Requires-Dist: setuptools-scm; extra == "dev"
